MANIFEST.in
README.txt
setup.py
docs/HISTORY.txt
src/smitheme/__init__.py
src/smitheme.phoenix.egg-info/PKG-INFO
src/smitheme.phoenix.egg-info/SOURCES.txt
src/smitheme.phoenix.egg-info/dependency_links.txt
src/smitheme.phoenix.egg-info/namespace_packages.txt
src/smitheme.phoenix.egg-info/not-zip-safe
src/smitheme.phoenix.egg-info/requires.txt
src/smitheme.phoenix.egg-info/top_level.txt
src/smitheme/phoenix/__init__.py
src/smitheme/phoenix/configure.zcml
src/smitheme/phoenix/skin.py
src/smitheme/phoenix/static/body_bg.png
src/smitheme/phoenix/static/gradient25.png
src/smitheme/phoenix/static/gradientdark.png
src/smitheme/phoenix/static/info.png
src/smitheme/phoenix/static/manage.png
src/smitheme/phoenix/static/middleground_bg.png
src/smitheme/phoenix/static/phoenix.css
src/smitheme/phoenix/static/reset.css
src/smitheme/phoenix/static/silva.ico
src/smitheme/phoenix/static/workspace_bg.png