Metadata-Version: 1.1
Name: smitheme.phoenix
Version: 1.0.1
Summary: SMI Skin for Silva 2.3
Home-page: https://github.com/silvacms/smitheme.phoenix
Author: Gert Hengeveld
Author-email: info@infrae.com
License: BSD
Keywords: skin silva smi
Platform: UNKNOWN
Classifier: Programming Language :: Python
Classifier: Topic :: Software Development :: Libraries :: Python Modules
